wave_front_h2ogpte/__init__.py
wave_front_h2ogpte/auth.py
wave_front_h2ogpte/h2oGPTe_connect.py
wave_front_h2ogpte-0.0.4.dist-info/METADATA
wave_front_h2ogpte-0.0.4.dist-info/WHEEL
wave_front_h2ogpte-0.0.4.dist-info/top_level.txt
wave_front_h2ogpte-0.0.4.dist-info/RECORD
