Metadata-Version: 2.1
Name: wave-front-h2ogpte
Version: 0.0.4
Requires-Dist: h2ogpte>=1.5.11
